dirhunter/__init__.py
dirhunter/core.py
dirhunter/utils.py
dirhunter-1.0.0.dist-info/METADATA
dirhunter-1.0.0.dist-info/WHEEL
dirhunter-1.0.0.dist-info/entry_points.txt
dirhunter-1.0.0.dist-info/top_level.txt
dirhunter-1.0.0.dist-info/RECORD
