Metadata-Version: 2.1
Name: dirhunter
Version: 1.0.0
Summary: A powerful directory scanning and hunting tool
Home-page: https://github.com/ByteBreach/dirhunter
Author: MrFidal
Author-email: mrfidal@proton.me
Classifier: Programming Language :: Python :: 3
Classifier: License :: OSI Approved :: MIT License
Classifier: Operating System :: OS Independent
Requires-Python: >=3.7
Requires-Dist: requests
Requires-Dist: colorama
Requires-Dist: click
